[
  {
    "move_number": 1,
    "player": "white",
    "timestamp": "2025-04-19T13:48:40.621607",
    "initial_image": "white_m1_initial.jpg",
    "current_image": "white_m1_current.jpg",
    "provider": "gemini",
    "move_notation": "b3",
    "from_square": "b2",
    "to_square": "b3",
    "piece_type": "pawn",
    "piece_color": "white",
    "captured_piece": null
  },
  {
    "move_number": 1,
    "player": "black",
    "timestamp": "2025-04-19T13:49:28.289758",
    "initial_image": "white_m1_current.jpg",
    "current_image": "black_m1_current.jpg",
    "provider": "gemini",
    "move_notation": "e5",
    "from_square": "e7",
    "to_square": "e5",
    "piece_type": "pawn",
    "piece_color": "black",
    "captured_piece": null
  },
  {
    "move_number": 2,
    "player": "white",
    "timestamp": "2025-04-19T13:49:38.382145",
    "initial_image": "black_m1_current.jpg",
    "current_image": "white_m2_current.jpg",
    "provider": "gemini",
    "move_notation": "c3",
    "from_square": "c2",
    "to_square": "b3",
    "piece_type": "pawn",
    "piece_color": "white",
    "captured_piece": null
  }
]